pytweet/__init__.py
pytweet/_tweet.py
pytweet/tweet.py
pytweet/utils.py
pytweet/sync/__init__.py
pytweet/sync/tweet.py
python_tweet-0.2.0.dist-info/LICENSE
python_tweet-0.2.0.dist-info/METADATA
python_tweet-0.2.0.dist-info/WHEEL
python_tweet-0.2.0.dist-info/top_level.txt
python_tweet-0.2.0.dist-info/RECORD
