Metadata-Version: 2.1
Name: python-tweet
Version: 0.2.0
Summary: A Python library for retrieving tweets from X (f.k.a. Twitter)
Author-email: Vladyslav Novotnyi <psejjkuczo@proxiedmail.com>
Maintainer-email: Vladyslav Novotnyi <psejjkuczo@proxiedmail.com>
License: The MIT License (MIT)
Project-URL: Homepage, https://github.com/fabelx/py-tweet
Project-URL: Bug Reports, https://github.com/fabelx/py-tweet/issues
Project-URL: Source, https://github.com/fabelx/py-tweet
Keywords: twitter,x,tweet,api
Classifier: Development Status :: 4 - Beta
Classifier: Intended Audience :: End Users/Desktop
Classifier: License :: OSI Approved :: MIT License
Classifier: Operating System :: OS Independent
Classifier: Programming Language :: Python :: 3
Classifier: Programming Language :: Python :: 3.12
Classifier: Programming Language :: Python :: 3.13
Classifier: Programming Language :: Python :: 3 :: Only
Requires-Python: >=3.12
License-File: LICENSE
Requires-Dist: aiohttp
Requires-Dist: requests
Provides-Extra: dev
Requires-Dist: build ; extra == 'dev'
Requires-Dist: twine ; extra == 'dev'
Provides-Extra: lint
Requires-Dist: black ==23.12.0 ; extra == 'lint'
Requires-Dist: isort ==5.12.0 ; extra == 'lint'
Provides-Extra: pydantic
Requires-Dist: pydantic ; extra == 'pydantic'
Provides-Extra: test
Requires-Dist: pydantic ; extra == 'test'
Requires-Dist: coverage ; extra == 'test'
Requires-Dist: pytest ; extra == 'test'
Requires-Dist: pytest-asyncio ; extra == 'test'
Requires-Dist: pytest-cov ; extra == 'test'
Requires-Dist: gevent ; extra == 'test'
